{
  "project_info": {
    "project_number": "898205774734",
    "firebase_url": "https://fir-exm-43752.firebaseio.com",
    "project_id": "fir-exm-43752",
    "storage_bucket": "fir-exm-43752.appspot.com"
  },
  "client": [
    {
      "client_info": {
        "mobilesdk_app_id": "1:898205774734:android:6f61ebb61dd6b906",
        "android_client_info": {
          "package_name": "id.kido1611.firebase.example"
        }
      },
      "oauth_client": [
        {
          "client_id": "898205774734-gk6ij99s0arrsehjv7e6n5nfpijikh59.apps.googleusercontent.com",
          "client_type": 3
        }
      ],
      "api_key": [
        {
          "current_key": "AIzaSyCZ5UhBqDA66FlsLK7hGwmnwP2d_qGtZBU"
        }
      ],
      "services": {
        "analytics_service": {
          "status": 1
        },
        "appinvite_service": {
          "status": 1,
          "other_platform_oauth_client": []
        },
        "ads_service": {
          "status": 2
        }
      }
    }
  ],
  "configuration_version": "1"
}